{
  "account_name": "TEST, LLC", 
  "average_claim_count_in_last_3_years": 3.666667, 
  "division": 26, 
  "dnb": "791611122", 
  "effective_date": "12/25/2008", 
  "effective_year": 2008, 
  "financial_score": 79, 
  "number_of_claims_in_the_2nd_last_year": 1, 
  "number_of_claims_in_the_3rd_last_year": 0, 
  "number_of_claims_in_the_last_year": 10, 
  "percentage_vehicles_extra_heavy": 0.0, 
  "percentage_vehicles_heavy": 0.0, 
  "percentage_vehicles_light": 1.0, 
  "percentage_vehicles_medium": 0.0, 
  "policy_limit": 10000000, 
  "predominant_radius": "Intermediate", 
  "sic": 6726, 
  "sic_description": "Finance, Insurance, And Real Estate", 
  "state": "FL", 
  "underwriter": "ABC", 
  "vehicle_count": 23, 
  "zipcode": 70341
}