{
  "account_name": "TEST, LLC",
  "average_claim_count_in_last_3_years": 3.0,
  "division": 21,
  "dnb": "10650162",
  "effective_date": "07/02/2010",
  "effective_year": 2010,
  "financial_score": 13,
  "number_of_claims_in_the_2nd_last_year": 7,
  "number_of_claims_in_the_3rd_last_year": 0,
  "number_of_claims_in_the_last_year": 2,
  "percentage_vehicles_extra_heavy": 0.030000000000000027,
  "percentage_vehicles_heavy": 0.22,
  "percentage_vehicles_light": 0.65,
  "percentage_vehicles_medium": 0.1,
  "policy_limit": 1000000,
  "predominant_radius": "Long",
  "sic": 2241,
  "sic_description": "Manufacturing",
  "state": "ME",
  "underwriter": "ABC",
  "vehicle_count": 23,
  "zipcode": 32739
}