{
  "account_name": "TEST, LLC",
  "average_claim_count_in_last_3_years": 3.666667,
  "division": 82,
  "dnb": "74075668",
  "effective_date": "02/14/2009",
  "effective_year": 2009,
  "financial_score": 43,
  "number_of_claims_in_the_2nd_last_year": 5,
  "number_of_claims_in_the_3rd_last_year": 1,
  "number_of_claims_in_the_last_year": 5,
  "percentage_vehicles_extra_heavy": 0.010000000000000009,
  "percentage_vehicles_heavy": 0.02,
  "percentage_vehicles_light": 0.22,
  "percentage_vehicles_medium": 0.75,
  "policy_limit": 5000000,
  "predominant_radius": "Intermediate",
  "sic": 2088,
  "sic_description": "Manufacturing",
  "state": "WI",
  "underwriter": "ABC",
  "vehicle_count": 6,
  "zipcode": 15459
}